agi_steps/__init__.py
agi_steps/__main__.py
agi_steps/py.typed
agi_steps/steps.py
agi_steps-0.1.9.dist-info/METADATA
agi_steps-0.1.9.dist-info/WHEEL
agi_steps-0.1.9.dist-info/RECORD
