Metadata-Version: 2.4
Name: agi-steps
Version: 0.1.9
Summary: Framework para gerenciamento e execução de etapas (steps) configuráveis em Python. Permite organizar scripts em grupos, ativar/desativar etapas e customizar configurações via dicionários.
Author-email: Moacyr Rodrigues Neto <moacyr.neto@agi.com.br>
License-Expression: MIT
Requires-Python: >=3.11
Requires-Dist: tomli>=2.2.1
